polycode.py
polycode-1.0.12.dist-info/METADATA
polycode-1.0.12.dist-info/RECORD
polycode-1.0.12.dist-info/WHEEL
polycode-1.0.12.dist-info/entry_points.txt
polycode-1.0.12.dist-info/top_level.txt
