Metadata-Version: 2.1
Name: polycode
Version: 1.0.12
Summary: Translate your code to a different spoken language
Home-page: https://github.com/froothacks/polycode
Author: David Gu
License: UNKNOWN
Platform: UNKNOWN
Requires-Dist: requests
